{
  "angle": "cause-purpose",
  "tactic": "positioning-statement",
  "hook_type": "if_then",
  "funnel": "TOF",
  "content_type": "meta-ad",
  "creative_brief": "Split frame: left side shows a generic supermarket barcode on shrink-wrapped meat, cold and anonymous. Right side shows a hand-written farm name tag on butcher paper (e.g. 'Bundarra Farm, NSW') with warm, natural light. Clean typography overlays the if/then hook.",
  "generated_at": "2026-04-05T02:44:53.197251",
  "ad_id": "BR-110",
  "primary_text": "If you can name your barista but not a single farmer who feeds your family, something broke.\n\nThe food system buried them. Thousands of kilometres of cold chain, wholesalers, and barcodes sit between you and the person who grew your dinner.\n\nFarmThru is a grocery store built to reverse that. Every product traces to a named farm. Bundarra pork from NSW. Wild-caught salmon from Collins on the South Coast. Paris Creek bio-dynamic dairy from South Australia.\n\nNo middlemen. No warehouses. No subscriptions. Order when you want, collect from Brookvale Monday to Friday.\n\nThis is becoming something bigger. You can own a piece of it.",
  "headline": "Name the farmer who fed you last",
  "description": "Farm-direct groceries from real producers. No lock-in, no middlemen.",
  "cta": "cfe_campaign"
}
